Workbook

Sheet Modelo
H5: Transaccion
D6: Estrategias | H6: codTRX
B7: Cliente | D7: cod_estrategia | H7: Tipo_TRX
B8: cod_cliente | D8: nombre_estrategia | H8: cod_protocolo
B9: nombre | D9: tipo_estrategia | H9: estado
B10: dni | D10: cod_gesto
B11: tipo_cliente | D11: min interes
B12: edad | D12: max interes
B13: sexo
H17: MOV-INTERACCIONES
H18: canal
H19: correlativo
H20: id_interaccion
H21: cod_cliente
H22: cod_estrategia
H23: cod_gesto
H24: cod_producto
H25: tipo_transaccion
H26: fecha
H27: hora
H28: nivel_de_interes
D30: Cuenta-Productos
D31: cod_lote_producto
D32: nombre_producto
D33: fecha_creacion_stock
D34: total_disponible
D35: total_vendidos
D36: total_veces_mostrado
D37: estado_producto
H43: canal
H44: correlativo
H45: cod_cliente
H46: cod_estrategia
H47: tipo_transaccion
H48: fecha
H49: hora

Sheet TABLA PROPUESTAS
J4: TABLAS MAESTRAS
J5: MAESTRA - PRODUCTOS
J6: Atributo | K6: Tipo | L6: Tamaño | M6: Clave | O6: Diseño Físico
J7: cod_lote_producto | K7: char | L7: 8 | M7: PK | O7: Nombre | P7: MAESTRA - PRODUCTOS
J8: nombre_producto | K8: varchar | L8: 20 | M8: SK | O8: Organización | P8: indexada
J9: fecha_creacion_stock | K9: date | L9: 8 | M9: -- | O9: Longitud de Registro | P9: (53,53)
J10: total_disponible | K10: int | L10: 4 | M10: -- | O10: IC | P10: 1024
J11: total_vendidos | K11: int | L11: 4 | M11: -- | O11: Capacidad | P11: N=1000000, AC=19*12*18
J12: cierres_venta
J13: total_veces_mostrado | K13: int | L13: 4 | M13: --
A14: TABLAS DE MOVIMIENTOS | J14: estado_producto | K14: char | L14: 1 | M14: --
A15: BITÁCORA INTERACCIONES
A16: Atributo | B16: Tipo | C16: Tamaño | D16: Clave
A17: canal | B17: char | C17: 1 | D17: PK
A18: correlativo | B18: int | C18: 4 | F18: Nombre | G18: BITÁCORA INTERACCIONES | J18: MAESTRA - CLIENTES
A19: cod_cliente | B19: char | C19: 8 | D19: SK | F19: Organización | G19: Indexado | J19: Atributo | K19: Tipo | L19: Tamaño | M19: Clave
A20: id_proceso_venta | B20: date | C20: 6 | F20: Longitud de Registro | G20: (67,67) | J20: cod_cliente | K20: char | L20: 8 | M20: PK
A21: tipo_cliente | B21: char | C21: 4 | D21: FK | F21: IC | G21: 512 | J21: nombre_cliente | K21: varchar | L21: 20 | M21: SK | O21: Nombre | P21: MAESTRA - CLIENTES
A22: cod_estrategia | B22: char | C22: 8 | D22: FK | F22: Capacidad | G22: N=1000000, AC= 19*24*7 | J22: fecha_ingreso | K22: date | L22: 8 | M22: -- | O22: Organización | P22: indexada
A23: cod_gesto | B23: char | C23: 8 | D23: FK | J23: cant_entradas | K23: int | L23: 7 | M23: -- | O23: Longitud de Registro | P23: (68,68)
A24: cod_producto | B24: char | C24: 8 | D24: FK | J24: total_cierres_ventas | K24: int | L24: 6 | M24: -- | O24: IC | P24: 512
A25: tipo_transaccion | B25: char | C25: 4 | D25: -- | J25: última_visita | K25: date | L25: 8 | M25: -- | O25: Capacidad | P25: N=1000000, AC= 19*24*7
A26: fecha | B26: date | C26: 8 | D26: -- | J26: estado_cliente | K26: char | L26: 1 | M26: --
A27: hora | B27: date | C27: 8 | D27: --
A28: nivel_de_interes | B28: float | C28: 2 | D28: --
J32: MAESTRA - ESTRATEGIAS
A33: BITÁCORA VENTAS | J33: Atributo | K33: Tipo | L33: Tamaño | M33: Clave
A34: Atributo | B34: Tipo | C34: Tamaño | D34: Clave | J34: cod_estrategia | K34: char | L34: 8 | M34: PK | O34: Nombre | P34: MAESTRA - ESTRATEGIAS
A35: canal | B35: =VLOOKUP(A35, 'Hoja 1'!$A$43:$D$57, 2, FALSE) -> #REF! | C35: 1 | D35: PK | F35: Nombre | G35: BITÁCORA VENTAS | J35: nombre_estrategia | K35: varchar | L35: 20 | M35: SK | O35: Organización | P35: indexada
A36: correlativo | B36: =VLOOKUP(A36, 'Hoja 1'!$A$43:$D$57, 2, FALSE) -> #REF! | C36: 4 | F36: Organización | G36: Indexado | J36: tipo_cliente | K36: char | L36: 6 | M36: -FK | O36: Longitud de Registro | P36: (37,37)
A37: cod_cliente | B37: =VLOOKUP(A37, 'Hoja 1'!$A$43:$D$57, 2, FALSE) -> #REF! | C37: 8 | D37: SK | F37: Longitud de Registro | G37: (41,41) | J37: total_veces_aplicada | K37: int | L37: 4 | M37: -- | O37: IC | P37: 1536
A38: cod_producto | B38: char | C38: 8 | D38: FK | E38: FK | F38: IC | G38: 1024 | J38: ventas_generadas | K38: int | L38: 4 | M38: -- | O38: Capacidad | P38: N=1000000, AC= 19*6*38
A39: cantidad | B39: int | C39: 3 | D39: --- | F39: Capacidad | G39: N=1000000, AC= 19*12*23 | J39: estado | K39: char | L39: 1 | M39: --
A40: cod_estrategia | B40: =VLOOKUP(A40, 'Hoja 1'!$A$43:$D$57, 2, FALSE) -> #REF! | C40: 8 | D40: FK
A41: tipo_transaccion | B41: =VLOOKUP(A41, 'Hoja 1'!$A$43:$D$57, 2, FALSE) -> #REF! | C41: 4 | D41: --
A42: fecha | B42: =VLOOKUP(A42, 'Hoja 1'!$A$43:$D$57, 2, FALSE) -> #REF! | C42: 8 | D42: -- | J42: E1
A43: hora | B43: =VLOOKUP(A43, 'Hoja 1'!$A$43:$D$57, 2, FALSE) -> #REF! | C43: 8 | D43: -- | J43: E2
J44: E3
J45: E4
A46: BITÁCORA DETALLE VENTA
A47: Atributo | B47: Tipo | C47: Tamaño | D47: Clave
A48: canal_venta | B48: char | C48: 1 | D48: PK | F48: Nombre | G48: BITÁCORA DETALLE VENTA
A49: correlativo | B49: int | C49: 4 | F49: Organización | G49: Indexado
A50: cod_lote_producto | B50: char | C50: 8 | F50: Longitud de Registro | G50: (17,17)
A51: cantidad | B51: int | C51: 4 | D51: -- | F51: IC | G51: 512
F52: Capacidad | G52: N=1000000, AC= 19*24*23
F69: W | G69: 1 | H69: C000001 | I69: 45812 | J69: T0001 | K69: E000001 | L69: G000001 | M69: 0000000 | N69: TRX0001 | O69: 0.3759838 | P69: 60
F70: W | G70: 2 | H70: C000001 | I70: 45812 | J70: T0001 | K70: E000002 | L70: G000002 | M70: P000002 | N70: TRX0002 | O70: 0.37866898 | P70: 75
F71: W | G71: 3 | H71: C000001 | I71: 45812 | J71: T0001 | K71: E000003 | L71: G000003 | M71: P000003 | N71: TRX0003 | O71: 0.38020833 | P71: 90
F72: W | G72: 4 | H72: C000001 | I72: 45812 | J72: T0001 | K72: E000003 | L72: G000004 | M72: P000004 | N72: TRX0004 | O72: 0.3818287 | P72: 100
B77: CASO 1: BITÁCORA INTERACCIONES
P78: MAESTRA PRODUCTOS
B79: canal | C79: correlativo | D79: cod_cliente | E79: id_proceso_venta | F79: tipo_cliente | G79: cod_estrategia | H79: cod_gesto | I79: cod_lote_producto | J79: tipo_transaccion | K79: fecha | L79: hora | M79: nivel_de_interes
B80: W | C80: 0001 | D80: C0000002 | E80: I00001 | F80: T00001 | G80: E0000012 | H80: G0000004 | I80: 00000000 | J80: TRX0003 | K80: 45812 | L80: 09:12:11 | M80: 70 | P80: cod_lote_producto | Q80: nombre_producto | R80: fecha_creacion_stock | S80: total_disponible | T80: total_vendidos | U80: total_veces_mostrado | V80: estado_producto
B81: ... | C81: ... | D81: ... | E81: ... | F81: ,,, | G81: ... | H81: ... | I81: ... | J81: ... | K81: ... | L81: ... | M81: ... | P81: ... | Q81: ... | R81: ... | S81: ... | T81: ... | U81: ... | V81: ...
B82: ... | C82: ... | D82: ... | E82: ... | F82: ... | G82: ... | H82: ... | I82: ... | J82: ... | K82: ... | L82: ... | M82: ... | P82: P0000005 | Q82: Camiseta básica | R82: 45048 | S82: 50 | T82: 150 | U82: 18 | V82: Activo
B83: ... | C83: ... | D83: ... | E83: ... | F83: ... | G83: ... | H83: ... | I83: ... | J83: ... | K83: ... | L83: ... | M83: ... | P83: ... | Q83: ... | R83: ... | S83: ... | T83: ... | U83: ... | V83: ...
B86: canal | C86: correlativo | D86: cod_cliente | E86: id_proceso_venta | F86: tipo_cliente | G86: cod_estrategia | H86: cod_gesto | I86: cod_lote_producto | J86: tipo_transaccion | K86: fecha | L86: hora | M86: nivel_de_interes | P86: cod_lote_producto | Q86: nombre_producto | R86: fecha_creacion_stock | S86: total_disponible | T86: total_vendidos | U86: total_veces_mostrado | V86: estado_producto
B87: W | C87: 0001 | D87: C0000002 | E87: I00001 | F87: T00001 | G87: E0000012 | H87: G0000004 | I87: 00000000 | J87: TRX0003 | K87: 45812 | L87: 09:12:11 | M87: 70 | P87: ... | Q87: ... | R87: ... | S87: ... | T87: ... | U87: ... | V87: ...
B88: W | C88: 0002 | D88: C0000002 | E88: I00001 | F88: T00001 | G88: E0000002 | H88: G0000002 | I88: P0000005 | J88: TRX0004 | K88: 45812 | L88: 09:13:12 | M88: 90 | P88: P0000005 | Q88: Camiseta básica | R88: 45048 | S88: 50 | T88: 150 | U88: 19 | V88: Activo
B89: ... | C89: ... | D89: ... | E89: ... | F89: ... | H89: ... | I89: ... | J89: ... | K89: ... | L89: ... | M89: ... | P89: ... | Q89: ... | R89: ... | S89: ... | T89: ... | U89: ... | V89: ...
B90: ... | C90: ... | D90: ... | E90: ... | F90: ... | G90: ... | H90: ... | I90: ... | J90: ... | K90: ... | L90: ... | M90: ...
P91: cod_lote_producto | Q91: nombre_producto | R91: fecha_creacion_stock | S91: total_disponible | T91: total_vendidos | U91: total_veces_mostrado | V91: estado_producto
P92: ... | Q92: ... | R92: ... | S92: ... | T92: ... | U92: ... | V92: ...
B93: canal | C93: correlativo | D93: cod_cliente | E93: id_proceso_venta | F93: tipo_cliente | G93: cod_estrategia | H93: cod_gesto | I93: cod_lote_producto | J93: tipo_transaccion | K93: fecha | L93: hora | M93: nivel_de_interes | P93: P0000005 | Q93: Camiseta básica | R93: 45048 | S93: 49 | T93: 151 | U93: 19 | V93: Activo
B94: W | C94: 0001 | D94: C0000002 | E94: I00001 | F94: T00001 | G94: E0000012 | H94: G0000004 | I94: 00000000 | J94: TRX0003 | K94: 45812 | L94: 09:12:11 | M94: 70 | P94: ... | Q94: ... | R94: ... | S94: ... | T94: ... | U94: ... | V94: ...
B95: W | C95: 0002 | D95: C0000002 | E95: I00001 | F95: T00001 | G95: E0000002 | H95: G0000002 | I95: P0000005 | J95: TRX0004 | K95: 45812 | L95: 09:13:12 | M95: 90
B96: W | C96: 0003 | D96: C0000002 | E96: I00001 | F96: T00001 | G96: E0000003 | H96: G0000006 | I96: P0000005 | J96: TRX0005 | K96: 45812 | L96: 09:13:47 | M96: 100
B97: ... | C97: ... | D97: ... | E97: ... | F97: ... | G97: ... | H97: ... | I97: ... | J97: ... | K97: ... | L97: ... | M97: ...
B98: ... | C98: ... | D98: ... | E98: ... | F98: ... | G98: ... | H98: ... | I98: ... | J98: ... | K98: ... | L98: ... | M98: ...
B101: BITACORA VENTAS
B102: canal | C102: correlativo | D102: cod_cliente | E102: cod_estrategia | F102: tipo_transaccion | G102: fecha | H102: hora
B103: W | C103: 0001 | D103: C0000002 | E103: E0000003 | F103: TRX0005 | G103: 45812 | H103: 0.38457176
B104: ... | C104: ... | D104: ... | E104: ... | F104: ... | G104: ... | H104: ...
B106: DETALLE VENTA
B107: canal_venta | C107: correlativo | D107: cod_lote_producto | E107: cantidad
B108: W | C108: 0001 | D108: P0000005 | E108: 1
B109: ... | C109: ... | D109: ... | E109: ...
B129: CASO 2: BITACORA INTERACCIONES
P130: MAESTRA PRODUCTOS
B131: canal | C131: correlativo | D131: cod_cliente | E131: id_proceso_venta | F131: tipo_cliente | G131: cod_estrategia | H131: cod_gesto | I131: cod_lote_producto | J131: tipo_transaccion | K131: fecha | L131: hora | M131: nivel_de_interes
B132: ... | C132: ... | D132: ... | E132: ... | F132: ... | G132: ... | H132: ... | I132: ... | J132: ... | K132: ... | L132: ... | M132: ... | P132: cod_lote_producto | Q132: nombre_producto | R132: fecha_creacion_stock | S132: total_disponible | T132: total_vendidos | U132: total_veces_mostrado | V132: estado_producto
B133: A | C133: 0001 | D133: C0000023 | E133: I00002 | F133: T00003 | G133: E0000012 | H133: G0000004 | I133: 00000000 | J133: TRX0003 | K133: 45803 | L133: 17:20:11 | M133: 30 | P133: ... | Q133: ... | R133: ... | S133: ... | T133: ... | U133: ... | V133: ...
B134: ... | C134: ... | D134: ... | E134: ... | F134: ... | G134: ... | H134: ... | I134: ... | J134: ... | K134: ... | L134: ... | M134: ... | P134: P0000024 | Q134: Pantalon gris | R134: 45690 | S134: 33 | T134: 120 | U134: 20 | V134: Activo
B135: ... | C135: ... | D135: ... | E135: ... | F135: ... | G135: ... | H135: ... | I135: ... | J135: ... | K135: ... | L135: ... | M135: ... | P135: P0000028 | Q135: Jean clásico | R135: 45690 | S135: 18 | T135: 160 | U135: 37 | V135: Activo
P136: ... | Q136: ... | R136: ... | S136: ... | T136: ... | U136: ... | V136: ...
B137: canal | C137: correlativo | D137: cod_cliente | E137: id_proceso_venta | F137: tipo_cliente | G137: cod_estrategia | H137: cod_gesto | I137: cod_lote_producto | J137: tipo_transaccion | K137: fecha | L137: hora | M137: nivel_de_interes
B138: ... | C138: ... | D138: ... | E138: ... | F138: ... | G138: ... | H138: ... | I138: ... | J138: ... | K138: ... | L138: ... | M138: ...
B139: A | C139: 0001 | D139: C0000023 | E139: I00002 | F139: T00003 | G139: E0000012 | H139: G0000004 | I139: 00000000 | J139: TRX0003 | K139: 45803 | L139: 17:20:11 | M139: 30 | P139: cod_lote_producto | Q139: nombre_producto | R139: fecha_creacion_stock | S139: total_disponible | T139: total_vendidos | U139: total_veces_mostrado | V139: estado_producto
B140: A | C140: 0002 | D140: C0000023 | E140: I00002 | F140: T00003 | G140: E0000001 | H140: G0000008 | I140: P0000024 | J140: TRX0003 | K140: 45803 | L140: 17:21:11 | M140: 80 | P140: ... | Q140: ... | R140: ... | S140: ... | T140: ... | U140: ... | V140: ...
B141: ... | C141: ... | D141: ... | E141: ... | F141: ... | G141: ... | H141: ... | I141: ... | J141: ... | K141: ... | L141: ... | M141: ... | P141: P0000024 | Q141: Pantalon gris | R141: 45690 | S141: 33 | T141: 120 | U141: 21 | V141: Activo
B142: ... | C142: ... | D142: ... | E142: ... | F142: ... | G142: ... | H142: ... | I142: ... | J142: ... | K142: ... | L142: ... | M142: ... | P142: P0000028 | Q142: Jean clásico | R142: 45690 | S142: 18 | T142: 160 | U142: 37 | V142: Activo
P143: ... | Q143: ... | R143: ... | S143: ... | T143: ... | U143: ... | V143: ...
B144: canal | C144: correlativo | D144: cod_cliente | E144: id_proceso_venta | F144: tipo_cliente | G144: cod_estrategia | H144: cod_gesto | I144: cod_lote_producto | J144: tipo_transaccion | K144: fecha | L144: hora | M144: nivel_de_interes
B145: ... | C145: ... | D145: ... | E145: ... | F145: ... | G145: ... | H145: ... | I145: ... | J145: ... | K145: ... | L145: ... | M145: ...
B146: A | C146: 0001 | D146: C0000023 | E146: I00002 | F146: T00003 | G146: E0000012 | H146: G0000004 | I146: 00000000 | J146: TRX0003 | K146: 45803 | L146: 17:20:11 | M146: 30 | P146: cod_lote_producto | Q146: nombre_producto | R146: fecha_creacion_stock | S146: total_disponible | T146: total_vendidos | U146: total_veces_mostrado | V146: estado_producto
B147: A | C147: 0002 | D147: C0000023 | E147: I00002 | F147: T00003 | G147: E0000001 | H147: G0000008 | I147: P0000024 | J147: TRX0003 | K147: 45803 | L147: 17:21:11 | M147: 80 | P147: ... | Q147: ... | R147: ... | S147: ... | T147: ... | U147: ... | V147: ...
B148: A | C148: 0003 | D148: C0000023 | E148: I00002 | F148: T00003 | G148: E0000002 | H148: G0000011 | I148: P0000028 | J148: TRX0003 | K148: 45803 | L148: 17:22:11 | M148: 90 | P148: P0000024 | Q148: Pantalon gris | R148: 45690 | S148: 33 | T148: 120 | U148: 19 | V148: Activo
B149: ... | C149: ... | D149: ... | E149: ... | F149: ... | G149: ... | H149: ... | I149: ... | J149: ... | K149: ... | L149: ... | M149: ... | P149: P0000028 | Q149: Jean clásico | R149: 45690 | S149: 18 | T149: 160 | U149: 38 | V149: Activo
P150: ... | Q150: ... | R150: ... | S150: ... | T150: ... | U150: ... | V150: ...
...

Sheet Consulta crítica
E2: Consulta de Cierres de venta por Tipo de producto
K3: Maestra clientes | M3: cod_cliente | N3: nombre | O3: apellido
F4: Tipo de producto | G4: T00002 | K4: Maestra productos | M4: cod_producto | N4: nombre | O4: tipo_producto | P4: total_ventasxtipoProducto (se conseguira a treves de calculo)
K5: Estrategias | M5: cod_estrategia | N5: nombre_estrategia
K6: bitacora venta | M6: cantidad | N6: fecha | O6: hora
F7: Nombre tipo | G7: Casaca
C13: cod cliente | D13: nombre | E13: apellido | F13: cod_producto | G13: nombre_producto | H13: cantidad | I13: cod_estrategia | J13: nombre_estrategia | K13: fecha | L13: hora
C14: C0000001 | D14: Diego | E14: Moran | F14: P0000001 | G14: Casaca Ultimate | H14: 3 | I14: E000001 | J14: Oferta persuasiva | K14: 24/'02/2025 | L14: 0.50212963 | M14: Ver detalles
C15: C0000002 | D15: Steven | E15: Cadillo | F15: P0000002 | G15: Casaca Ligth | H15: 1 | I15: E000008 | J15: Producto alternativo | K15: 45680 | L15: 0.5437963 | M15: Ver detalles
C16: C0000003 | D16: Tino | E16: Reyna | F16: P0000003 | G16: Casaca Deluxe Verano | H16: 2 | I16: E000005 | J16: Producto alternativo | K16: ´10/01/2025 | L16: 0.58546296 | M16: Ver detalles
C17: ... | D17: ... | E17: ... | F17: .. | G17: ... | H17: ... | I17: ... | J17: ... | K17: ... | L17: ... | M17: ...
F20: 1 | G20: 2 | H20: 3 | I20: 4 | J20: 5
D25: DISEÑO LÓGICO
D27: tipo_producto | E27: char | F27: 6 | G27: PK | J27: clave primaria | K27: tipo_producto
D28: nombre_tipo_producto | E28: char | F28: 10 | G28: SK | J28: clave secundaria | K28: nombre_tipo_producto
D29: total_ventas | E29: int | F29: 3
D30: ventas | E30: ´1-99
E32: cod_cliente | F32: char | G32: 8 | H32: FK
E33: nombre | F33: char | G33: 20
E34: apellido | F34: char | G34: 20
E35: cod_producto | F35: char | G35: 8
E36: nombre_producto | F36: char | G36: 20
E37: cantidad | F37: int | G37: 3
E38: cod_estrategia | F38: char | G38: 8
E39: nombre_estrategia | F39: char | G39: 20
E40: fecha | F40: date | G40: 8
E41: hora | F41: date | G41: 8
B44: a. | C44: Nombre | D44: Tabla consulta Cierres de ventas - tipo Producto
C45: Organizacion | D45: Indexada
C46: Clave-Primaria | D46: tipo_producto
C47: Clave-Secundaria | D47: nombre_tipo_producto | K47: RL | L47: ER
H48: 10216 | K48: 0 | L48: 508
B49: b. | C49: Longitud-Registro | D49: (12196,2479) | J49: 512 | K49: 0 | L49: 1020
J50: 1024 | K50: 0 | L50: 10
B51: c. | C51: Espacio Libre | D51: (0,0) | J51: 1536 | K51: 0 | L51: 1532
J52: 2048 | K52: 1 | L52: 2044
B53: d. | C53: Longitud de BLOQUE (IC) | D53: 2560 | J53: 2560 | K53: 1 | L53: 74 | M53: se elige este
J54: 3072 | K54: 1 | L54: 1098
B55: e. | C55: Longitud de EXTENT (AC) | D55: 19*3*1 RLS | J55: 3584 | K55: 1 | L55: 1610
B57: f. | C57: Capacidad | D57: (N=1000000, AC= 19*3*2 RLS)
J58: IC | L58: RL | N58: ER
I59: 2479 | J59: 512 | K59: =(J59-4)/($I$59+3) -> 0.20467365 | L59: =INT(K59) -> 0 | M59: =K59-L59 -> 0.20467365 | N59: =M59*($I$59+3) -> 508
J60: 1024 | K60: =(J60-4)/($I$59+3) -> 0.4109589 | L60: =INT(K60) -> 0 | M60: =K60-L60 -> 0.4109589 | N60: =M60*($I$59+3) -> 1020
J61: 1536 | K61: =(J61-4)/($I$59+3) -> 0.61724416 | L61: =INT(K61) -> 0 | M61: =K61-L61 -> 0.61724416 | N61: =M61*($I$59+3) -> 1532
J62: 2048 | K62: =(J62-4)/($I$59+3) -> 0.82352941 | L62: =INT(K62) -> 0 | M62: =K62-L62 -> 0.82352941 | N62: =M62*($I$59+3) -> 2044
J63: 2560 | K63: =(J63-4)/($I$59+3) -> 1.0298147 | L63: =INT(K63) -> 1 | M63: =K63-L63 -> 0.029814666 | N63: =M63*($I$59+3) -> 74
J64: 3072 | K64: =(J64-4)/($I$59+3) -> 1.2360999 | L64: =INT(K64) -> 1 | M64: =K64-L64 -> 0.23609992 | N64: =M64*($I$59+3) -> 586
B65: En la carpeta se encuentra el diagrama | J65: 3584 | K65: =(J65-4)/($I$59+3) -> 1.4423852 | L65: =INT(K65) -> 1 | M65: =K65-L65 -> 0.44238517 | N65: =M65*($I$59+3) -> 1098
